wannierbuilder/__init__.py
wannierbuilder/math/__init__.py
wannierbuilder/math/geometry.py
wannierbuilder/math/linalg.py
wannierbuilder/math/pert.py
wannierbuilder/plot/__init__.py
wannierbuilder/plot/plot.py
wannierbuilder/plot/testpath.py
wannierbuilder/scdm/__init__.py
wannierbuilder/scdm/density_scdmk.py
wannierbuilder/scdm/downfolder.py
wannierbuilder/scdm/eigen_modifer.py
wannierbuilder/scdm/ijR_potential.py
wannierbuilder/scdm/lwf.py
wannierbuilder/scdm/myTB.py
wannierbuilder/scdm/mytb.py
wannierbuilder/scdm/normalize.py
wannierbuilder/scdm/scdmk.py
wannierbuilder/scdm/w90_parser.py
wannierbuilder/utils/__init__.py
wannierbuilder/utils/kpoints.py
wannierbuilder/utils/nckit.py
wannierbuilder/utils/supercell.py
wannierbuilder/utils/symbol.py
wannierbuilder/wrapper/__init__.py
wannierbuilder/wrapper/gpawwrapper.py
wannierbuilder/wrapper/ifcwrapper.py
wannierbuilder/wrapper/ijR.py
wannierbuilder/wrapper/myTB.py
wannierbuilder/wrapper/phonopywrapper.py
wannierbuilder/wrapper/sislwrapper.py
wannierbuilder/wrapper/utils.py
wannierbuilder/wrapper/w90_parser.py
wannierbuilder/wrapper/wannier90.py
wannierbuilder-0.1.5.data/scripts/phonopy_to_netcdf.py
wannierbuilder-0.1.5.dist-info/LICENSE
wannierbuilder-0.1.5.dist-info/METADATA
wannierbuilder-0.1.5.dist-info/WHEEL
wannierbuilder-0.1.5.dist-info/top_level.txt
wannierbuilder-0.1.5.dist-info/RECORD
